yajwiz/__init__.py
yajwiz/analyzer.py
yajwiz/boqwiz.py
yajwiz/cg.py
yajwiz/data.json
yajwiz/grammar_check.py
yajwiz/grammar_rules.py
yajwiz/pos_tagger.py
yajwiz/tables.py
yajwiz/types.py
yajwiz-0.10.4.dist-info/LICENSE
yajwiz-0.10.4.dist-info/METADATA
yajwiz-0.10.4.dist-info/WHEEL
yajwiz-0.10.4.dist-info/top_level.txt
yajwiz-0.10.4.dist-info/RECORD
