Metadata-Version: 2.1
Name: yajwiz
Version: 0.10.4
Summary: Klingon NLP toolkit
Author: Iikka Hauhio
Author-email: fergusq@kaivos.org
Classifier: Programming Language :: Python :: 3
Requires-Python: >=3.8
License-File: LICENSE
Requires-Dist: appdirs
Requires-Dist: requests
